{
	"spriteSheet":"overworld",

	"layers":[
		{
			"tiles":[
		{
			"name":"sky",
			"ranges":[
				[
					0,200,
					0,27
				]
			]
		},
		{
			"name":"ground",
			"type":"ground",
			"ranges":[
				[
					0,200,
					24,4
				]
			]
		},
		{
			"name":"chocolate",
			"type":"ground",
			"ranges":[
				[
					27,10,
					18,1
				]
			]
		},
		{
			"pattern":"pipe-3h",
			"ranges":[
				[
					20,1,
					20,1
				]
			]
		},
		{
			"name":"chance",
			"type":"ground",
			"ranges":[
				[
					185,3,
					12,1
				]
			]
		},
		{
			"name":"chance",
			"type":"ground",
			"ranges":[
				[
					184,1,
					13,1
				]
			]
		},
		{
			"name":"chance",
			"type":"ground",
			"ranges":[
				[
					183,1,
					14,3
				]
			]
		},
		{
			"name":"chance",
			"type":"ground",
			"ranges":[
				[
					184,1,
					17,1
				]
			]
		},
		{
			"name":"chance",
			"type":"ground",
			"ranges":[
				[
					185,2,
					18,1
				]
			]
		},
		{
			"name":"chance",
			"type":"ground",
			"ranges":[
				[
					186,2,
					16,1
				]
			]
		},
		{
			"name":"chance",
			"type":"ground",
			"ranges":[
				[
					188,1,
					16,3
				]
			]
		},
		{
			"name":"chance",
			"type":"ground",
			"ranges":[
				[
					192,1,
					12,6
				]
			]
		},
		{
			"name":"chance",
			"type":"ground",
			"ranges":[
				[
					192,6,
					18,1
				]
			]
		},
		{
			"name":"chocolate",
			"type":"ground",
			"ranges":[
				[
					183,15,
					22,2
				]
			]
		},
		{
			"name":"chocolate",
			"type":"ground",
			"ranges":[
				[
					184,13,
					21,1
				]
			]
		}
	]
		}
	],
	"patterns":{
		"cloud":{
			"tiles":[
				{
					"name":"cloud-1-1",
					"ranges":[
						[0,0]
					]
				},
				{
					"name":"cloud-1-2",
					"ranges":[
						[1,0]
					]
				},
				{
					"name":"cloud-1-3",
					"ranges":[
						[2,0]
					]
				},
				{
					"name":"cloud-2-1",
					"ranges":[
						[0,1]
					]
				},
				{
					"name":"cloud-2-2",
					"ranges":[
						[1,1]
					]
				},
				{
					"name":"cloud-2-3",
					"ranges":[
						[2,1]
					]
				}
			]
		},
		"pipe-2h":{
			"tiles":[
				{
					"name":"pipe-insert-vert-left",
					"type":"ground",
					"ranges":[
						[
							0,0
						]
					]
				},
				{
					"name":"pipe-insert-vert-right",
					"type":"ground",
					"ranges":[
						[
							1,0
						]
					]
				},
				{
					"pattern":"pipe-vert",
					"ranges":[
						[0,1,
						1,2]
					]
				}
			]
		},
		"pipe-3h":{
			"tiles":[
				{
					"name":"pipe-insert-vert-left",
					"type":"ground",
					"ranges":[
						[
							0,0
						]
					]
				},
				{
					"name":"pipe-insert-vert-right",
					"type":"ground",
					"ranges":[
						[
							1,0
						]
					]
				},
				{
					"pattern":"pipe-vert",
					"ranges":[
						[0,1,
						1,3]
					]
				}
			]
		},

		"pipe-vert":{
			"tiles":[
				{
					"name":"pipe-vert-left",
					"type":"ground",
					"ranges":[
						[
							0,1,
							0,1
						]
					]
				},
				{
					"name":"pipe-vert-right",
					"type":"ground",
					"ranges":[
						[
							1,1,
							0,1
						]
					]
				}
			]
		}
	}
}
